giphy_dev_ti/__init__.py
giphy_dev_ti/api_client.py
giphy_dev_ti/api_response.py
giphy_dev_ti/configuration.py
giphy_dev_ti/exceptions.py
giphy_dev_ti/py.typed
giphy_dev_ti/rest.py
giphy_dev_ti/api/__init__.py
giphy_dev_ti/api/gifs_api.py
giphy_dev_ti/api/stickers_api.py
giphy_dev_ti/models/__init__.py
giphy_dev_ti/models/get_gifs_by_id200_response.py
giphy_dev_ti/models/gif.py
giphy_dev_ti/models/gif_images.py
giphy_dev_ti/models/gif_images_downsized.py
giphy_dev_ti/models/gif_images_downsized_large.py
giphy_dev_ti/models/gif_images_downsized_medium.py
giphy_dev_ti/models/gif_images_downsized_small.py
giphy_dev_ti/models/gif_images_downsized_still.py
giphy_dev_ti/models/gif_images_fixed_height.py
giphy_dev_ti/models/gif_images_fixed_height_downsampled.py
giphy_dev_ti/models/gif_images_fixed_height_small.py
giphy_dev_ti/models/gif_images_fixed_height_small_still.py
giphy_dev_ti/models/gif_images_fixed_height_still.py
giphy_dev_ti/models/gif_images_fixed_width.py
giphy_dev_ti/models/gif_images_fixed_width_downsampled.py
giphy_dev_ti/models/gif_images_fixed_width_small.py
giphy_dev_ti/models/gif_images_fixed_width_small_still.py
giphy_dev_ti/models/gif_images_fixed_width_still.py
giphy_dev_ti/models/gif_images_looping.py
giphy_dev_ti/models/gif_images_original.py
giphy_dev_ti/models/gif_images_original_still.py
giphy_dev_ti/models/gif_images_preview.py
giphy_dev_ti/models/gif_images_preview_gif.py
giphy_dev_ti/models/image.py
giphy_dev_ti/models/meta.py
giphy_dev_ti/models/pagination.py
giphy_dev_ti/models/random_gif200_response.py
giphy_dev_ti/models/user.py
giphy_dev_ti-0.0.1.dist-info/METADATA
giphy_dev_ti-0.0.1.dist-info/WHEEL
giphy_dev_ti-0.0.1.dist-info/top_level.txt
giphy_dev_ti-0.0.1.dist-info/RECORD
